README.md
setup.py
pyhakoot/__init__.py
pyhakoot.egg-info/PKG-INFO
pyhakoot.egg-info/SOURCES.txt
pyhakoot.egg-info/dependency_links.txt
pyhakoot.egg-info/requires.txt
pyhakoot.egg-info/top_level.txt