Metadata-Version: 2.1
Name: pyhakoot
Version: 1.0.3
Summary: A python package to interact with Kahoot! (reupload)
Home-page: https://github.com/theusaf/KahootPY
Author: theusaf
Author-email: theusafyt@gmail.com
License: UNKNOWN
Keywords: kahoot,bot
Platform: UNKNOWN
Classifier: Programming Language :: Python :: 3
Classifier: License :: OSI Approved :: MIT License
Classifier: Operating System :: OS Independent
Requires-Python: >=3.6
